xayagametest/__init__.py
xayagametest/game.py
xayagametest/premine.py
xayagametest/testcase.py
xayagametest/xaya.py
xayagametest-1.0.3.dist-info/licenses/AUTHORS
xayagametest-1.0.3.dist-info/licenses/COPYING
xayagametest-1.0.3.dist-info/METADATA
xayagametest-1.0.3.dist-info/WHEEL
xayagametest-1.0.3.dist-info/top_level.txt
xayagametest-1.0.3.dist-info/RECORD
