Metadata-Version: 2.4
Name: xayagametest
Version: 1.0.3
Summary: Testing framework for Xaya GSPs
Author-email: Daniel Kraft <d@domob.eu>
License: The MIT License (MIT)
Project-URL: Homepage, https://xaya.io
Project-URL: Repository, https://github.com/xaya/libxayagame
Classifier: Programming Language :: Python :: 3
Classifier: Operating System :: OS Independent
Classifier: License :: OSI Approved :: MIT License
Requires-Python: >=3.9
License-File: COPYING
License-File: AUTHORS
Requires-Dist: jsonrpclib-pelix
Dynamic: license-file
